{"anli.test.864": {"hyp1": [{"anli.test.864.qcpg.hyp1.9": "It was 2 hours later."}, {"anli.test.864.qcpg.hyp1.7": "It was just after a couple of hours."}, {"anli.test.864.qcpg.hyp1.6": "It's two hours later."}, {"anli.test.864.qcpg.hyp1.5": "A couple hours later."}, {"anli.test.864.qcpg.hyp1.4": "A couple of hours later."}, {"anli.test.864.qcpg.hyp1.2": "After about 2 hours."}, {"anli.test.864.qcpg.hyp1.1": "After two hours."}, {"anli.test.864.qcpg.hyp1.0": "Two hours later."}], "hyp2": [{"anli.test.864.qcpg.hyp2.24": "Waitress has mistaken our orders."}, {"anli.test.864.qcpg.hyp2.0": "The waiter had erroneous orders."}]}, "anli.test.2621": {"hyp1": [{"anli.test.2621.qcpg.hyp1.57": "Jerry's chosen to get a space heater for his room."}, {"anli.test.2621.qcpg.hyp1.48": "Jerry's chosen to get a heater for his room."}, {"anli.test.2621.qcpg.hyp1.6": "Jerry's decided to get a space heater for his room."}]}, "anli.test.2986": {"hyp1": [{"anli.test.2986.qcpg.hyp1.4": "She's decided to buy self-tanner in the drug store."}]}, "anli.test.2187": {"hyp1": [{"anli.test.2187.qcpg.hyp1.2": "Louie saw that he needed food for cheap."}]}, "anli.test.2495": {"hyp1": [{"anli.test.2495.qcpg.hyp1.21": "A big ice cream cone I've ate."}, {"anli.test.2495.qcpg.hyp1.13": "Oh, I've been eating a giant ice cream cone."}, {"anli.test.2495.qcpg.hyp1.10": "A big ice cream cone I ate."}, {"anli.test.2495.qcpg.hyp1.5": "I've been eating a giant ice cream cone."}, {"anli.test.2495.qcpg.hyp1.1": "I've been eating the huge ice cream cone."}, {"anli.test.2495.qcpg.hyp1.0": "I've been eating the big ice cream cone."}]}, "anli.test.292": {"hyp1": [{"anli.test.292.qcpg.hyp1.40": "Woman didn't like the U.S. at war."}, {"anli.test.292.qcpg.hyp1.33": "Woman didn't like the U.S. at the war."}, {"anli.test.292.qcpg.hyp1.25": "Woman didn't like the U.S. involved in the war."}, {"anli.test.292.qcpg.hyp1.1": "Woman didn't like the idea that America was at war."}], "hyp2": [{"anli.test.292.qcpg.hyp2.1": "Vietnam started to lose the war."}, {"anli.test.292.qcpg.hyp2.0": "Vietnam had begun to lose the war."}]}, "anli.test.1516": {"hyp1": [{"anli.test.1516.qcpg.hyp1.27": "All of a sudden, it was a thunderstorm."}, {"anli.test.1516.qcpg.hyp1.25": "All of a sudden, a thunderstorm sounded."}, {"anli.test.1516.qcpg.hyp1.23": "All of a sudden, a thunderstorm erupted."}, {"anli.test.1516.qcpg.hyp1.22": "It had started a thunderstorm all of a sudden."}, {"anli.test.1516.qcpg.hyp1.19": "It had started, abruptly,storming."}, {"anli.test.1516.qcpg.hyp1.15": "All of a sudden, the storm began."}, {"anli.test.1516.qcpg.hyp1.10": "The storm, abruptly, began."}, {"anli.test.1516.qcpg.hyp1.9": "The storm began suddenly."}, {"anli.test.1516.qcpg.hyp1.8": "The storm had started, abruptly."}, {"anli.test.1516.qcpg.hyp1.5": "It was suddenly a storm."}, {"anli.test.1516.qcpg.hyp1.4": "It had started to rain all of a sudden."}, {"anli.test.1516.qcpg.hyp1.3": "It was suddenly a thunderstorm."}, {"anli.test.1516.qcpg.hyp1.1": "Suddenly, it was a storm."}, {"anli.test.1516.qcpg.hyp1.0": "All of a sudden, it was a storm."}], "hyp2": [{"anli.test.1516.qcpg.hyp2.23": "It was getting hot."}, {"anli.test.1516.qcpg.hyp2.16": "It had begun to be hot."}, {"anli.test.1516.qcpg.hyp2.2": "It was starting to get hot."}]}, "anli.test.1857": {"hyp1": [{"anli.test.1857.qcpg.hyp1.14": "Kelly's ordering water."}, {"anli.test.1857.qcpg.hyp1.12": "Kelly has just ordered water."}, {"anli.test.1857.qcpg.hyp1.8": "Well, kelly has ordered water."}, {"anli.test.1857.qcpg.hyp1.7": "Kelly ordered water."}, {"anli.test.1857.qcpg.hyp1.3": "Well, kelly ordered water."}, {"anli.test.1857.qcpg.hyp1.1": "Kelly's ordering the water."}, {"anli.test.1857.qcpg.hyp1.0": "Kelly has ordered water."}], "hyp2": [{"anli.test.1857.qcpg.hyp2.16": "Kelly's lost her keys, and she's got no spares."}, {"anli.test.1857.qcpg.hyp2.15": "Kelly's lost her keys, and she's got no spare."}, {"anli.test.1857.qcpg.hyp2.7": "Kelly's lost her keys and she's got no spare."}, {"anli.test.1857.qcpg.hyp2.3": "Kelly's lost her keys and hasn't got any spares."}]}, "anli.test.413": {"hyp1": [{"anli.test.413.qcpg.hyp1.9": "The Cleaner was there."}, {"anli.test.413.qcpg.hyp1.8": "The Cleaner was inside."}, {"anli.test.413.qcpg.hyp1.6": "There was a cleaner man in there."}, {"anli.test.413.qcpg.hyp1.5": "There was a cleaner there."}, {"anli.test.413.qcpg.hyp1.1": "The cleaner was in there."}, {"anli.test.413.qcpg.hyp1.0": "And the cleaner was in there."}]}, "anli.test.187": {"hyp1": [{"anli.test.187.qcpg.hyp1.25": "Danny wanted a pet, his wife wanted dogs."}, {"anli.test.187.qcpg.hyp1.14": "Well, danny wanted a pet and his wife was in love with dogs."}, {"anli.test.187.qcpg.hyp1.13": "Well, Danny wanted to have a pet, and his wife was in love with the dogs"}, {"anli.test.187.qcpg.hyp1.11": "Danny wanted a pet, his wife was in love with dogs."}, {"anli.test.187.qcpg.hyp1.10": "Well, Danny wanted a pet and his wife loved dogs."}, {"anli.test.187.qcpg.hyp1.7": "Danny wanted a pet, his wife's in love with dogs."}, {"anli.test.187.qcpg.hyp1.3": "Danny wanted a pet and his wife loved dogs."}, {"anli.test.187.qcpg.hyp1.2": "Danny wanted a pet and his wife was in love with dogs."}, {"anli.test.187.qcpg.hyp1.1": "Danny wanted a pet, and his wife was in love with dogs."}], "hyp2": [{"anli.test.187.qcpg.hyp2.19": "Danny's wife raised cats because she had a fear of dogs."}]}, "anli.test.2885": {"hyp1": [{"anli.test.2885.qcpg.hyp1.30": "Ann's been so sad, her mother's surgery tomorrow."}, {"anli.test.2885.qcpg.hyp1.24": "Ann was so upset, because her mom had surgery tomorrow."}, {"anli.test.2885.qcpg.hyp1.23": "Ann was so upset, because her mum had surgery tomorrow."}, {"anli.test.2885.qcpg.hyp1.15": "Ann's been so sad because her mom's surgery tomorrow."}, {"anli.test.2885.qcpg.hyp1.14": "It's just that Ann was sad, because her mom's surgery tomorrow."}, {"anli.test.2885.qcpg.hyp1.12": "It's just that Ann was sad, because her mother had surgery tomorrow."}, {"anli.test.2885.qcpg.hyp1.11": "Ann's been sad because her mom's surgery tomorrow."}, {"anli.test.2885.qcpg.hyp1.10": "It's just that Ann was sad because her mother had surgery tomorrow."}, {"anli.test.2885.qcpg.hyp1.9": "Anne's been sad because her mother's surgery tomorrow."}, {"anli.test.2885.qcpg.hyp1.8": "It's just that Ann was sad because her mother's surgery tomorrow."}, {"anli.test.2885.qcpg.hyp1.7": "It's just that Ann was sad, because her mother's surgery tomorrow."}, {"anli.test.2885.qcpg.hyp1.4": "Ann's been sad because her mother's surgery tomorrow."}, {"anli.test.2885.qcpg.hyp1.3": "Ann's been so sad because her mother's surgery tomorrow."}, {"anli.test.2885.qcpg.hyp1.1": "Ann was sad because her mother had surgery tomorrow."}, {"anli.test.2885.qcpg.hyp1.0": "Ann was so upset, because her mother had surgery tomorrow."}], "hyp2": [{"anli.test.2885.qcpg.hyp2.7": "Ann found a video of a chef who made a joke that she liked."}, {"anli.test.2885.qcpg.hyp2.6": "Ann found a video of chef making a joke that she liked."}]}, "anli.test.1481": {"hyp1": [{"anli.test.1481.qcpg.hyp1.0": "Goose was the one that led Sam."}]}, "anli.test.1550": {"hyp1": [{"anli.test.1550.qcpg.hyp1.3": "Jodie's dream was to feed peanuts to elephants."}, {"anli.test.1550.qcpg.hyp1.2": "Jodie's thinking of feeding peanuts to elephants."}], "hyp2": [{"anli.test.1550.qcpg.hyp2.11": "Jodie's dream was to ride the elephant to her yard."}]}, "anli.test.379": {"hyp1": [{"anli.test.379.qcpg.hyp1.2": "Ed's got the keys."}], "hyp2": [{"anli.test.379.qcpg.hyp2.7": "Ed's lost his keys."}, {"anli.test.379.qcpg.hyp2.3": "Ed lost his keys."}, {"anli.test.379.qcpg.hyp2.2": "Ed's keys have been lost."}, {"anli.test.379.qcpg.hyp2.1": "Ed had lost his keys."}]}, "anli.test.418": {"hyp1": [{"anli.test.418.qcpg.hyp1.13": "Our time was good."}, {"anli.test.418.qcpg.hyp1.12": "We've had a great time."}, {"anli.test.418.qcpg.hyp1.10": "We've had a very good time."}, {"anli.test.418.qcpg.hyp1.9": "We've had a good time."}, {"anli.test.418.qcpg.hyp1.7": "You know, we've had a good time."}, {"anli.test.418.qcpg.hyp1.5": "A good time we've had."}, {"anli.test.418.qcpg.hyp1.3": "A good time we had."}], "hyp2": [{"anli.test.418.qcpg.hyp2.34": "My wife and daughter... they had a bath and a sauna."}, {"anli.test.418.qcpg.hyp2.25": "My wife and daughter, they were having a bath, they were having a sauna."}, {"anli.test.418.qcpg.hyp2.19": "My wife and daughter, they were having a bath and a sauna."}, {"anli.test.418.qcpg.hyp2.17": "My wife and daughter were in the process of massage and sauna."}, {"anli.test.418.qcpg.hyp2.13": "My wife and my daughter both had a bath and a sauna."}, {"anli.test.418.qcpg.hyp2.11": "My wife and daughter were having a bath and a sauna."}, {"anli.test.418.qcpg.hyp2.10": "I mean, my wife and my daughter had a massage and the sauna."}, {"anli.test.418.qcpg.hyp2.9": "I mean, my wife and my daughter have had a massage and a sauna."}, {"anli.test.418.qcpg.hyp2.6": "My wife and daughter, they had a massage and a sauna."}, {"anli.test.418.qcpg.hyp2.5": "My wife and daughter, they had a bath and a sauna."}, {"anli.test.418.qcpg.hyp2.4": "My wife and daughter have been having a bath and a sauna."}, {"anli.test.418.qcpg.hyp2.3": "My wife and daughter had a bath and a sauna."}, {"anli.test.418.qcpg.hyp2.2": "My wife and daughter had been in a sauna and a bath."}]}, "anli.test.1138": {"hyp1": [{"anli.test.1138.qcpg.hyp1.2": "Well, Preslie's got a secret ingredient."}, {"anli.test.1138.qcpg.hyp1.0": "Preslie's got a secret ingredient."}], "hyp2": [{"anli.test.1138.qcpg.hyp2.28": "He'd got a secret to get a dead horse."}, {"anli.test.1138.qcpg.hyp2.26": "He'd got a little bit of a secret to buy an old dead horse."}, {"anli.test.1138.qcpg.hyp2.24": "He kept secretly purchasing an old dead horse."}, {"anli.test.1138.qcpg.hyp2.23": "He kept secretly purchasing an old horse that was dead."}, {"anli.test.1138.qcpg.hyp2.21": "His secret had been to buy an old dead horse."}, {"anli.test.1138.qcpg.hyp2.20": "His secret was to buy an old dead horse."}, {"anli.test.1138.qcpg.hyp2.19": "He's got a secret to get a dead horse."}, {"anli.test.1138.qcpg.hyp2.18": "His secret had been to buy the old dead horse."}, {"anli.test.1138.qcpg.hyp2.17": "His secret was to buy the old dead horse."}, {"anli.test.1138.qcpg.hyp2.15": "A secret of his would have bought an old dead horse."}, {"anli.test.1138.qcpg.hyp2.13": "He's got a secret to get a horse that's dead."}, {"anli.test.1138.qcpg.hyp2.12": "He had a secret, buying an old dead horse."}, {"anli.test.1138.qcpg.hyp2.11": "He kept secretly buying an old horse that was dead."}, {"anli.test.1138.qcpg.hyp2.9": "A secret of his would buy an old dead horse."}, {"anli.test.1138.qcpg.hyp2.8": "A secret of his would be to buy an old dead horse."}, {"anli.test.1138.qcpg.hyp2.4": "He had a secret, and he bought an old dead horse."}, {"anli.test.1138.qcpg.hyp2.3": "He's got a secret to buy an old dead horse."}, {"anli.test.1138.qcpg.hyp2.2": "He had a secret to buy an old dead horse."}]}, "anli.test.2859": {"hyp1": [{"anli.test.2859.qcpg.hyp1.17": "Eileen Old Fitbit is a wreck."}], "hyp2": [{"anli.test.2859.qcpg.hyp2.51": "Eileen wants her phone app accurate."}, {"anli.test.2859.qcpg.hyp2.38": "Eileen wants her phone information to be accurate."}, {"anli.test.2859.qcpg.hyp2.8": "Eileen's looking to get the phone app accurate."}, {"anli.test.2859.qcpg.hyp2.7": "Eileen's looking to get a phone app accurate."}, {"anli.test.2859.qcpg.hyp2.6": "Eileen's looking to make sure her cell phone is right."}, {"anli.test.2859.qcpg.hyp2.4": "Eileen's looking to get the exact information on the phone."}]}, "anli.test.26": {"hyp1": [{"anli.test.26.qcpg.hyp1.30": "He was smart, he had known all kinds of info."}, {"anli.test.26.qcpg.hyp1.24": "He was smart, he had known all kinds of information."}, {"anli.test.26.qcpg.hyp1.17": "He was smart, he had information."}, {"anli.test.26.qcpg.hyp1.14": "He had a smart mind and knew something."}, {"anli.test.26.qcpg.hyp1.5": "He was smart, and he knew information."}, {"anli.test.26.qcpg.hyp1.4": "He had a smart mind and knew the information."}, {"anli.test.26.qcpg.hyp1.0": "He had a smart mind and knew a little bit."}], "hyp2": [{"anli.test.26.qcpg.hyp2.28": "Evan was taking his tests on his own."}, {"anli.test.26.qcpg.hyp2.17": "Evan's tests were taken by him."}, {"anli.test.26.qcpg.hyp2.16": "Well, evan's testing by himself."}, {"anli.test.26.qcpg.hyp2.6": "Evan's taken up the test by himself."}, {"anli.test.26.qcpg.hyp2.2": "Evan had taken his tests by himself."}, {"anli.test.26.qcpg.hyp2.1": "Evan had taken on his own tests."}]}, "anli.test.814": {"hyp1": [{"anli.test.814.qcpg.hyp1.11": "My friend's got a few good qualities, and he's paying late."}, {"anli.test.814.qcpg.hyp1.5": "My friend's got a few good qualities, paying a late payment."}, {"anli.test.814.qcpg.hyp1.2": "My roommate's got a few good qualities, paying a late payment."}], "hyp2": [{"anli.test.814.qcpg.hyp2.23": "I taught my roommate to be organized."}, {"anli.test.814.qcpg.hyp2.20": "I've taught my roommate to be organized."}, {"anli.test.814.qcpg.hyp2.6": "I've taught my roommate how to be organized."}, {"anli.test.814.qcpg.hyp2.5": "I taught my roommate the way to organise."}, {"anli.test.814.qcpg.hyp2.2": "I taught my roommate how to be organized."}]}, "anli.test.2465": {"hyp1": [{"anli.test.2465.qcpg.hyp1.23": "Alissa saw bullfighting, but it was too dull for her."}, {"anli.test.2465.qcpg.hyp1.20": "Alissa visited bullfight, but it was too dull for her."}, {"anli.test.2465.qcpg.hyp1.14": "Alissa saw the bullfight, but it was too dull for her."}, {"anli.test.2465.qcpg.hyp1.13": "Alissa visited bullfight, but it was too dull."}, {"anli.test.2465.qcpg.hyp1.9": "Alissa visited bullfighting, but it was too tedious."}, {"anli.test.2465.qcpg.hyp1.8": "Alissa visited bullfight, but it was too boring for her."}, {"anli.test.2465.qcpg.hyp1.6": "Alissa visited bullfighting, but it was too tedious for her."}, {"anli.test.2465.qcpg.hyp1.5": "Alissa sees the bullfight, but it's too dull for her."}, {"anli.test.2465.qcpg.hyp1.4": "Alissa visited bullfighting, but it had been too dull for her."}, {"anli.test.2465.qcpg.hyp1.3": "Alissa sees the bullfight, but it's just too boring for her"}, {"anli.test.2465.qcpg.hyp1.2": "Alissa visited bullfighting, but it was too boring for her."}], "hyp2": [{"anli.test.2465.qcpg.hyp2.21": "The bull-fighting center was visited by alissa."}, {"anli.test.2465.qcpg.hyp2.14": "Alyssa's been to see a bull fighting place."}, {"anli.test.2465.qcpg.hyp2.12": "The bull-fighting arena was visited by alissa."}, {"anli.test.2465.qcpg.hyp2.10": "Alissa's been to see the bull fighting field."}, {"anli.test.2465.qcpg.hyp2.9": "Alissa's been to see the bullfighting arena."}, {"anli.test.2465.qcpg.hyp2.8": "Alissa's been to see the bullfighting area."}, {"anli.test.2465.qcpg.hyp2.6": "Alissa has come to the bullfighting area."}]}, "anli.test.2069": {"hyp1": [{"anli.test.2069.qcpg.hyp1.33": "Neil's missed a train to Budapest."}, {"anli.test.2069.qcpg.hyp1.28": "Neil's missed Budapest train."}, {"anli.test.2069.qcpg.hyp1.27": "Neil's missed a train trip to Budapest."}, {"anli.test.2069.qcpg.hyp1.20": "Neil had ceased to make the journey to Budapest."}, {"anli.test.2069.qcpg.hyp1.15": "Neil's lost a train to Budapest."}, {"anli.test.2069.qcpg.hyp1.14": "The train to Budapest was missed by Neil."}, {"anli.test.2069.qcpg.hyp1.5": "Neil's lost his train to Budapest."}, {"anli.test.2069.qcpg.hyp1.4": "Neil has lost his train to Budapest."}, {"anli.test.2069.qcpg.hyp1.2": "Neil had a missed train to Budapest."}, {"anli.test.2069.qcpg.hyp1.1": "Neil had a missed train going to Budapest."}], "hyp2": [{"anli.test.2069.qcpg.hyp2.18": "Neil was really into exploring new things."}, {"anli.test.2069.qcpg.hyp2.12": "Neil's fond of exploring new spots."}, {"anli.test.2069.qcpg.hyp2.11": "Neil's fond of exploring new places."}, {"anli.test.2069.qcpg.hyp2.10": "Neil's really fond of exploring new things."}, {"anli.test.2069.qcpg.hyp2.9": "Neil's fond of exploring new things."}, {"anli.test.2069.qcpg.hyp2.2": "Neil liked to explore new places."}]}, "anli.test.952": {"hyp1": [{"anli.test.952.qcpg.hyp1.7": "Lenny's choice was to make museums his main career."}, {"anli.test.952.qcpg.hyp1.4": "Lenny's choice was to make the museum his main career."}, {"anli.test.952.qcpg.hyp1.3": "Lenny decided that the museum would be one of his major career."}], "hyp2": [{"anli.test.952.qcpg.hyp2.14": "Another Museum near Lenny refused Lenny to work."}, {"anli.test.952.qcpg.hyp2.2": "Another museum near Lenny rejected Lenny to work."}]}, "anli.test.383": {"hyp1": [{"anli.test.383.qcpg.hyp1.1": "Lance's children had refused sleep."}], "hyp2": [{"anli.test.383.qcpg.hyp2.27": "Lance was fighting his wife because she wasn't romantic."}, {"anli.test.383.qcpg.hyp2.26": "Lance fought against his wife because she was not romantic."}, {"anli.test.383.qcpg.hyp2.23": "Lance fought against his wife because she was not romantically motivated."}, {"anli.test.383.qcpg.hyp2.21": "Lance, instead, battled his wife, because she had no romantic feelings."}, {"anli.test.383.qcpg.hyp2.18": "Instead, France fought against his wife, because she was not romantically motivated."}, {"anli.test.383.qcpg.hyp2.11": "Lance, instead, battled with his wife, because she had no romantic feelings."}, {"anli.test.383.qcpg.hyp2.9": "Lance, instead, had a fight against his wife, because she had no romantic feelings."}, {"anli.test.383.qcpg.hyp2.4": "Lance was fighting his wife for not liking the romance."}, {"anli.test.383.qcpg.hyp2.3": "Lance had a fight against his wife, because she had no romantic feelings."}, {"anli.test.383.qcpg.hyp2.1": "Lance was fighting with his wife because she wasn't romantically motivated."}, {"anli.test.383.qcpg.hyp2.0": "Lance was fighting with his wife because she wasn't romantic."}]}, "anli.test.122": {"hyp1": [{"anli.test.122.qcpg.hyp1.41": "Sally's been photographing many things while she's been to see."}, {"anli.test.122.qcpg.hyp1.38": "Sally shot many photos when she visited."}, {"anli.test.122.qcpg.hyp1.32": "Sally was taking many photos when she visited."}, {"anli.test.122.qcpg.hyp1.30": "Sally's been taking many photos when she's gone to see."}, {"anli.test.122.qcpg.hyp1.24": "Sally's taken many photos when she's gone to see."}, {"anli.test.122.qcpg.hyp1.16": "Sally took many photos when she was sightseeing."}, {"anli.test.122.qcpg.hyp1.11": "Sally's taken many photos when she's sightseeing."}, {"anli.test.122.qcpg.hyp1.10": "Sally's been taking many photos when she's been to see the sights."}, {"anli.test.122.qcpg.hyp1.9": "Sally's been taking many photos when she's been to see."}, {"anli.test.122.qcpg.hyp1.7": "Sally had taken many photographs when she visited."}, {"anli.test.122.qcpg.hyp1.6": "Sally had taken many photos when she was in the city."}, {"anli.test.122.qcpg.hyp1.5": "Sally's taken a lot of photos when she's gone to see."}, {"anli.test.122.qcpg.hyp1.3": "Sally had many photographs when she was sightseeing."}], "hyp2": [{"anli.test.122.qcpg.hyp2.19": "Sally had photos of all the things that she had seen."}, {"anli.test.122.qcpg.hyp2.8": "Sally's got photos of all the things she's seen."}, {"anli.test.122.qcpg.hyp2.6": "Sally's been taking photos of all she's visits."}, {"anli.test.122.qcpg.hyp2.4": "Sally's been taking photos of every single visit."}]}, "anli.test.130": {"hyp1": [{"anli.test.130.qcpg.hyp1.6": "Marvin's girlfriend sarah joined, but her in a different location."}, {"anli.test.130.qcpg.hyp1.2": "Marvin's girlfriend sarah joined, but she's stationed somewhere"}], "hyp2": [{"anli.test.130.qcpg.hyp2.1": "Sarah had gone back to school, and Marvin had been waiting."}]}, "anli.test.1728": {"hyp1": [{"anli.test.1728.qcpg.hyp1.10": "The dog of Richard has returned today."}, {"anli.test.1728.qcpg.hyp1.9": "Richard's dog has come back tonight."}, {"anli.test.1728.qcpg.hyp1.8": "Richard's dog has returned today."}, {"anli.test.1728.qcpg.hyp1.7": "The dog of Richard has come back today."}, {"anli.test.1728.qcpg.hyp1.6": "Richard's Dog returned today."}, {"anli.test.1728.qcpg.hyp1.5": "On that day, the dog of Richard returned."}, {"anli.test.1728.qcpg.hyp1.4": "On that day, Richard's dog returned."}, {"anli.test.1728.qcpg.hyp1.2": "The dog of Richard returned today."}, {"anli.test.1728.qcpg.hyp1.0": "Richard's dog has come back today."}]}, "anli.test.419": {"hyp1": [{"anli.test.419.qcpg.hyp1.27": "Cat's found a way to stay and sleep."}, {"anli.test.419.qcpg.hyp1.25": "Cat found the way to stay and sleep."}, {"anli.test.419.qcpg.hyp1.8": "Cat found a way to stay in the carrier and sleep."}, {"anli.test.419.qcpg.hyp1.7": "Cat found out how to stay in the carrier and sleep."}, {"anli.test.419.qcpg.hyp1.2": "The cat found out how to stay in the state of carrier and sleep."}], "hyp2": [{"anli.test.419.qcpg.hyp2.5": "Cat always abandoned it."}]}, "anli.test.3016": {"hyp1": [{"anli.test.3016.qcpg.hyp1.19": "Oh, I've been drinking too many coffees."}, {"anli.test.3016.qcpg.hyp1.18": "I've been drinking too many Coffee."}, {"anli.test.3016.qcpg.hyp1.17": "Too much caffeine I've been drinking."}, {"anli.test.3016.qcpg.hyp1.15": "I've been drinking too many Coffees."}, {"anli.test.3016.qcpg.hyp1.12": "I'm consuming too much Coffee."}, {"anli.test.3016.qcpg.hyp1.10": "Took too much caffeine."}, {"anli.test.3016.qcpg.hyp1.9": "Drank too much of the caffeine."}, {"anli.test.3016.qcpg.hyp1.4": "I've been drinking too much Coffee."}, {"anli.test.3016.qcpg.hyp1.2": "I've been drinking too much caffeine."}, {"anli.test.3016.qcpg.hyp1.1": "I'm consuming too much caffeine."}], "hyp2": [{"anli.test.3016.qcpg.hyp2.16": "I've been having no caffeine."}, {"anli.test.3016.qcpg.hyp2.6": "I've been without caffeine for a while."}, {"anli.test.3016.qcpg.hyp2.3": "I had no caffeine."}, {"anli.test.3016.qcpg.hyp2.2": "I've had no caffeine."}, {"anli.test.3016.qcpg.hyp2.1": "I've had no coffee."}]}, "anli.test.1003": {"hyp1": [{"anli.test.1003.qcpg.hyp1.30": "Friend's family was vegan."}, {"anli.test.1003.qcpg.hyp1.21": "Friends had a family of them were vegans."}, {"anli.test.1003.qcpg.hyp1.17": "Friends Family's been vegan."}, {"anli.test.1003.qcpg.hyp1.2": "Friends family was Vegan."}, {"anli.test.1003.qcpg.hyp1.1": "Friends family was a Vegan."}]}, "anli.test.1126": {"hyp1": [{"anli.test.1126.qcpg.hyp1.21": "Molly's got into an accident."}, {"anli.test.1126.qcpg.hyp1.20": "Molly's been in a car crash."}, {"anli.test.1126.qcpg.hyp1.14": "Well, molly's got into an accident."}, {"anli.test.1126.qcpg.hyp1.12": "Molly's been in a car accident."}, {"anli.test.1126.qcpg.hyp1.4": "Molly's accident happened."}, {"anli.test.1126.qcpg.hyp1.2": "Molly's in an accident."}, {"anli.test.1126.qcpg.hyp1.1": "Molly had an accident."}, {"anli.test.1126.qcpg.hyp1.0": "Molly's been in an accident."}], "hyp2": [{"anli.test.1126.qcpg.hyp2.22": "During her trip, she became sticky."}, {"anli.test.1126.qcpg.hyp2.15": "When she was traveling, she became sticky."}, {"anli.test.1126.qcpg.hyp2.10": "She was sticky when she was traveling."}, {"anli.test.1126.qcpg.hyp2.6": "During her journey, she became sticky."}, {"anli.test.1126.qcpg.hyp2.5": "During her journey, she became very sticky."}, {"anli.test.1126.qcpg.hyp2.3": "She was so sticky when she was traveling."}, {"anli.test.1126.qcpg.hyp2.2": "She was sticky when she was on the plane."}, {"anli.test.1126.qcpg.hyp2.0": "She was a bit sticky when she was traveling."}]}, "anli.test.271": {"hyp2": [{"anli.test.271.qcpg.hyp2.34": "Forgot about the stuffing of bread."}, {"anli.test.271.qcpg.hyp2.30": "I've forgotten about the stuffing of bread."}, {"anli.test.271.qcpg.hyp2.25": "Forgot about the stuffing."}, {"anli.test.271.qcpg.hyp2.17": "I forgot about the bread."}]}, "anli.test.229": {"hyp2": [{"anli.test.229.qcpg.hyp2.1": "I was wondering if he wanted to change my diapers."}]}, "anli.test.1893": {"hyp2": [{"anli.test.1893.qcpg.hyp2.3": "Jake tried to do something he observed and failed."}, {"anli.test.1893.qcpg.hyp2.2": "Jake tried to do something that he observed and failed."}, {"anli.test.1893.qcpg.hyp2.0": "Jake was trying to do something that he saw and he failed."}]}, "anli.test.102": {"hyp2": [{"anli.test.102.qcpg.hyp2.38": "A bad storm ensued in the garden of Trish."}, {"anli.test.102.qcpg.hyp2.37": "The garden of Trish had been flooded with bad rain."}, {"anli.test.102.qcpg.hyp2.26": "A bad storm has occurred in Trish's garden."}, {"anli.test.102.qcpg.hyp2.25": "The garden of Trish had just been facing a storm."}, {"anli.test.102.qcpg.hyp2.24": "The garden of Trish had been facing a storm."}, {"anli.test.102.qcpg.hyp2.23": "Trish's garden had a bad storm."}, {"anli.test.102.qcpg.hyp2.22": "A bad storm in the garden of Trish."}, {"anli.test.102.qcpg.hyp2.21": "The garden of Trish had just been experiencing a storm."}, {"anli.test.102.qcpg.hyp2.19": "A bad thunderstorm ensued in the garden of Trish."}, {"anli.test.102.qcpg.hyp2.14": "A bad thunderstorm has occurred in the Trish garden."}, {"anli.test.102.qcpg.hyp2.13": "The storm was bad in Trish's garden."}, {"anli.test.102.qcpg.hyp2.11": "A bad storm has occurred in the garden of Trish."}, {"anli.test.102.qcpg.hyp2.10": "The Trish Garden has just experienced a storm."}, {"anli.test.102.qcpg.hyp2.9": "A bad storm has occurred in the Trish garden."}, {"anli.test.102.qcpg.hyp2.7": "The garden of Trish had suffered a bad storm."}, {"anli.test.102.qcpg.hyp2.6": "The garden of Trish had suffered a storm."}, {"anli.test.102.qcpg.hyp2.5": "A bad storm was in the garden of Trish."}, {"anli.test.102.qcpg.hyp2.3": "The storm was bad in the Trish garden."}, {"anli.test.102.qcpg.hyp2.0": "The garden of Trish had a bad storm."}]}}